LICENSE
syncopy/__init__.py
syncopy/connectivity/AV_compRoutines.py
syncopy/connectivity/ST_compRoutines.py
syncopy/connectivity/__init__.py
syncopy/connectivity/connectivity_analysis.py
syncopy/connectivity/csd.py
syncopy/connectivity/granger.py
syncopy/connectivity/wilson_sf.py
syncopy/datatype/__init__.py
syncopy/datatype/base_data.py
syncopy/datatype/continuous_data.py
syncopy/datatype/discrete_data.py
syncopy/datatype/methods/arithmetic.py
syncopy/datatype/methods/concat.py
syncopy/datatype/methods/copy.py
syncopy/datatype/methods/definetrial.py
syncopy/datatype/methods/redefinetrial.py
syncopy/datatype/methods/selectdata.py
syncopy/datatype/methods/show.py
syncopy/datatype/selector.py
syncopy/datatype/util.py
syncopy/io/__init__.py
syncopy/io/load_ft.py
syncopy/io/load_nwb.py
syncopy/io/load_spy_container.py
syncopy/io/load_tdt.py
syncopy/io/mne_conv.py
syncopy/io/nwb.py
syncopy/io/save_spy_container.py
syncopy/io/utils.py
syncopy/plotting/__init__.py
syncopy/plotting/_helpers.py
syncopy/plotting/_plotting.py
syncopy/plotting/config.py
syncopy/plotting/helpers.py
syncopy/plotting/mp_plotting.py
syncopy/plotting/sp_plotting.py
syncopy/plotting/spike_plotting.py
syncopy/plotting/spy_plotting.py
syncopy/preproc/__init__.py
syncopy/preproc/compRoutines.py
syncopy/preproc/firws.py
syncopy/preproc/preprocessing.py
syncopy/preproc/resampledata.py
syncopy/preproc/resampling.py
syncopy/shared/__init__.py
syncopy/shared/computational_routine.py
syncopy/shared/const_def.py
syncopy/shared/dask_helpers.py
syncopy/shared/errors.py
syncopy/shared/filetypes.py
syncopy/shared/input_processors.py
syncopy/shared/kwarg_decorators.py
syncopy/shared/latency.py
syncopy/shared/log.py
syncopy/shared/metadata.py
syncopy/shared/parsers.py
syncopy/shared/queries.py
syncopy/shared/tools.py
syncopy/specest/README.md
syncopy/specest/__init__.py
syncopy/specest/_norm_spec.py
syncopy/specest/compRoutines.py
syncopy/specest/fooofspy.py
syncopy/specest/freqanalysis.py
esi_syncopy-2023.9.dist-info/LICENSE
esi_syncopy-2023.9.dist-info/METADATA
esi_syncopy-2023.9.dist-info/WHEEL
esi_syncopy-2023.9.dist-info/RECORD
