Metadata-Version: 2.1
Name: esi-syncopy
Version: 2023.9
Summary: A toolkit for user-friendly large-scale electrophysiology data analysis. Syncopy is compatible with the Matlab toolbox FieldTrip.
Home-page: https://syncopy.org
License: BSD-3-Clause
Author: Stefan Fürtinger
Author-email: sfuerti@esi-frankfurt.de
Requires-Python: >=3.8,<3.12
Classifier: Environment :: Console
Classifier: Framework :: Jupyter
Classifier: License :: OSI Approved :: BSD License
Classifier: Operating System :: OS Independent
Classifier: Programming Language :: Python :: 3
Classifier: Programming Language :: Python :: 3.8
Classifier: Programming Language :: Python :: 3.9
Classifier: Programming Language :: Python :: 3.10
Classifier: Programming Language :: Python :: 3.11
Classifier: Topic :: Scientific/Engineering
Requires-Dist: bokeh (>=3.1.1,<4.0.0)
Requires-Dist: dask-jobqueue (>=0.8)
Requires-Dist: dask[distributed] (>=2022.6)
Requires-Dist: fooof (>=1.0)
Requires-Dist: h5py (>=2.9)
Requires-Dist: matplotlib (>=3.5)
Requires-Dist: natsort (>=8.1.0,<9.0.0)
Requires-Dist: numpy (>=1.10)
Requires-Dist: psutil (>=5.9)
Requires-Dist: scipy (>=1.10.0)
Requires-Dist: tqdm (>=4.31)
Project-URL: Repository, https://github.com/esi-neuroscience/syncopy
